oss_sustain_guard/__init__.py
oss_sustain_guard/bot_detection.py
oss_sustain_guard/cache.py
oss_sustain_guard/cli.py
oss_sustain_guard/config.py
oss_sustain_guard/core.py
oss_sustain_guard/dependency_graph.py
oss_sustain_guard/dependency_tree_resolver.py
oss_sustain_guard/http_client.py
oss_sustain_guard/repository.py
oss_sustain_guard/trend.py
oss_sustain_guard/assets/report_template.html
oss_sustain_guard/assets/demo/demo_results.json
oss_sustain_guard/cli_utils/__init__.py
oss_sustain_guard/cli_utils/cache_helpers.py
oss_sustain_guard/cli_utils/constants.py
oss_sustain_guard/cli_utils/display.py
oss_sustain_guard/cli_utils/helpers.py
oss_sustain_guard/cli_utils/loaders.py
oss_sustain_guard/cli_utils/output.py
oss_sustain_guard/commands/__init__.py
oss_sustain_guard/commands/cache.py
oss_sustain_guard/commands/check.py
oss_sustain_guard/commands/gratitude.py
oss_sustain_guard/commands/trace.py
oss_sustain_guard/commands/trend.py
oss_sustain_guard/dependency_parsers/__init__.py
oss_sustain_guard/dependency_parsers/base.py
oss_sustain_guard/dependency_parsers/resolver_helpers.py
oss_sustain_guard/dependency_parsers/csharp/__init__.py
oss_sustain_guard/dependency_parsers/csharp/nuget.py
oss_sustain_guard/dependency_parsers/dart/__init__.py
oss_sustain_guard/dependency_parsers/dart/pub.py
oss_sustain_guard/dependency_parsers/elixir/__init__.py
oss_sustain_guard/dependency_parsers/elixir/mix.py
oss_sustain_guard/dependency_parsers/go/__init__.py
oss_sustain_guard/dependency_parsers/go/gomod.py
oss_sustain_guard/dependency_parsers/go/modsum.py
oss_sustain_guard/dependency_parsers/haskell/__init__.py
oss_sustain_guard/dependency_parsers/haskell/cabal_stack.py
oss_sustain_guard/dependency_parsers/java/__init__.py
oss_sustain_guard/dependency_parsers/java/gradle_maven.py
oss_sustain_guard/dependency_parsers/javascript/__init__.py
oss_sustain_guard/dependency_parsers/javascript/bun.py
oss_sustain_guard/dependency_parsers/javascript/deno.py
oss_sustain_guard-0.23.1.dist-info/METADATA
oss_sustain_guard-0.23.1.dist-info/WHEEL
oss_sustain_guard-0.23.1.dist-info/entry_points.txt
oss_sustain_guard-0.23.1.dist-info/licenses/LICENSE
oss_sustain_guard-0.23.1.dist-info/RECORD
