Metadata-Version: 2.4
Name: oss-sustain-guard
Version: 0.23.1
Summary: Sustainability signals for OSS dependencies across ecosystems
Project-URL: Repository, https://github.com/onukura/oss-sustain-guard
Project-URL: Documentation, https://onukura.github.io/oss-sustain-guard/
Project-URL: Releases, https://github.com/onukura/oss-sustain-guard/releases
Project-URL: Issues, https://github.com/onukura/oss-sustain-guard/issues
Author-email: onukura <26293997+onukura@users.noreply.github.com>
License: MIT License
License-File: LICENSE
Classifier: Development Status :: 4 - Beta
Classifier: Environment :: Console
Classifier: Intended Audience :: Developers
Classifier: License :: OSI Approved :: MIT License
Classifier: Operating System :: OS Independent
Classifier: Programming Language :: Python
Classifier: Programming Language :: Python :: 3 :: Only
Classifier: Programming Language :: Python :: 3.10
Classifier: Programming Language :: Python :: 3.11
Classifier: Programming Language :: Python :: 3.12
Classifier: Programming Language :: Python :: 3.13
Classifier: Programming Language :: Python :: 3.14
Requires-Python: <3.15,>=3.10
Requires-Dist: aiofiles>=25.1.0
Requires-Dist: httpx>=0.28.1
Requires-Dist: networkx>=3.0
Requires-Dist: python-dotenv>=1.2.1
Requires-Dist: pyyaml>=6.0
Requires-Dist: rich>=14.2.0
Requires-Dist: scipy>=1.15.3
Requires-Dist: tomli>=2.0.0
Requires-Dist: typer>=0.20.0
